localization/__init__.py
localization/find_centroid.py
localization/geoInterface.py
localization/geoProject.py
localization/geometry.py
localization/methods.py
localization/shapely_2D.py
localization/shapely_earth1.py
localization/test/__init__.py
localization_patched-0.1.4.data/scripts/sample.py
localization_patched-0.1.4.dist-info/LICENSE.txt
localization_patched-0.1.4.dist-info/METADATA
localization_patched-0.1.4.dist-info/WHEEL
localization_patched-0.1.4.dist-info/top_level.txt
localization_patched-0.1.4.dist-info/RECORD
