Metadata-Version: 2.1
Name: localization-patched
Version: 0.1.4
Summary: Multilateration and triangulation.
Home-page: https://github.com/kamalshadi/Localization
Author: Kamal Shadi
Author-email: kamal.shadi85@gmail.com
License: LICENSE.txt
License-File: LICENSE.txt
Requires-Dist: scipy
Requires-Dist: shapely
Requires-Dist: descartes
